sopel_modules.inclusivity-0.2.0.post0-py3.12-nspkg.pth
sopel_modules/inclusivity/__init__.py
sopel_modules/inclusivity/inclusivity.py
tests/__init__.py
tests/test_inclusivity.py
sopel_modules.inclusivity-0.2.0.post0.dist-info/COPYING
sopel_modules.inclusivity-0.2.0.post0.dist-info/METADATA
sopel_modules.inclusivity-0.2.0.post0.dist-info/WHEEL
sopel_modules.inclusivity-0.2.0.post0.dist-info/namespace_packages.txt
sopel_modules.inclusivity-0.2.0.post0.dist-info/top_level.txt
sopel_modules.inclusivity-0.2.0.post0.dist-info/RECORD
