Metadata-Version: 2.1
Name: sopel_modules.inclusivity
Version: 0.2.0.post0
Summary: Old Inclusive Language plugin for Sopel - please update to sopel-inclusivity
Home-page: https://github.com/sopel-irc/sopel-inclusivity
Author: dgw
Author-email: dgw@technobabbl.es
License: Eiffel Forum License, version 2
License-File: COPYING
Requires-Dist: sopel <8,>=7.0
